tygle_docs/__init__.py
tygle_docs/base/__init__.py
tygle_docs/base/batch_update_request.py
tygle_docs/docs.py
tygle_docs/rest/__init__.py
tygle_docs/rest/documents.py
tygle_docs/types/__init__.py
tygle_docs/types/enums/__init__.py
tygle_docs/types/enums/content_alignment.py
tygle_docs/types/enums/suggestions_view_mode.py
tygle_docs/types/enums/unit.py
tygle_docs/types/requests/__init__.py
tygle_docs/types/requests/batch_update_body.py
tygle_docs/types/requests/delete_content_range_request.py
tygle_docs/types/requests/insert_inline_image_request.py
tygle_docs/types/requests/insert_table_request.py
tygle_docs/types/requests/models/__init__.py
tygle_docs/types/requests/models/end_of_segment_location.py
tygle_docs/types/requests/models/location.py
tygle_docs/types/requests/models/table_cell_location.py
tygle_docs/types/requests/models/table_range.py
tygle_docs/types/requests/replace_all_text_request.py
tygle_docs/types/requests/update_request.py
tygle_docs/types/requests/update_table_cell_style_request.py
tygle_docs/types/resources/__init__.py
tygle_docs/types/resources/body.py
tygle_docs/types/resources/document.py
tygle_docs/types/resources/models/__init__.py
tygle_docs/types/resources/models/dimension.py
tygle_docs/types/resources/models/size.py
tygle_docs/types/resources/named_ranges/__init__.py
tygle_docs/types/resources/named_ranges/named_range/__init__.py
tygle_docs/types/resources/named_ranges/named_range/named_range.py
tygle_docs/types/resources/named_ranges/named_range/range/__init__.py
tygle_docs/types/resources/named_ranges/named_range/range/range.py
tygle_docs/types/resources/named_ranges/named_ranges.py
tygle_docs/types/resources/structural_element/__init__.py
tygle_docs/types/resources/structural_element/paragraph/__init__.py
tygle_docs/types/resources/structural_element/paragraph/paragraph.py
tygle_docs/types/resources/structural_element/paragraph/paragraph_element/__init__.py
tygle_docs-0.1.13.dist-info/WHEEL
tygle_docs-0.1.13.dist-info/METADATA
tygle_docs-0.1.13.dist-info/RECORD
