Metadata-Version: 2.1
Name: tygle-docs
Version: 0.1.13
Summary: 
Author: shmookoff
Author-email: shmookoff@gmail.com
Requires-Python: >=3.10,<4.0
Classifier: Programming Language :: Python :: 3
Classifier: Programming Language :: Python :: 3.10
Requires-Dist: tygle (>=0.2,<0.3)
